ordeq_pymupdf/__init__.py
ordeq_pymupdf/_version.py
ordeq_pymupdf/pdf_file.py
ordeq_pymupdf/py.typed
ordeq_pymupdf-1.0.1.dist-info/licenses/LICENSE
ordeq_pymupdf-1.0.1.dist-info/METADATA
ordeq_pymupdf-1.0.1.dist-info/WHEEL
ordeq_pymupdf-1.0.1.dist-info/top_level.txt
ordeq_pymupdf-1.0.1.dist-info/RECORD
